package_query/__init__.py
package_query/client.py
package_query/constants.py
package_query/exceptions.py
package_query/http.py
package_query/mcp_server.py
package_query/models.py
package_query/providers/__init__.py
package_query/providers/base.py
package_query/providers/crates.py
package_query/providers/dockerhub.py
package_query/providers/github_actions.py
package_query/providers/npm.py
package_query/providers/pypi.py
package_query/py.typed
package_query-0.1.0.dist-info/WHEEL
package_query-0.1.0.dist-info/entry_points.txt
package_query-0.1.0.dist-info/METADATA
package_query-0.1.0.dist-info/RECORD
