Metadata-Version: 2.3
Name: package-query
Version: 0.1.0
Summary: Query latest package versions from PyPI, npm, crates.io, Docker Hub, and GitHub Actions
Keywords: mcp,pypi,npm,crates.io,docker,github actions
Author: Henrique
Author-email: Henrique <henriquemoreira10fk@gmail.com>
Classifier: Development Status :: 4 - Beta
Classifier: Intended Audience :: Developers
Classifier: License :: OSI Approved :: MIT License
Classifier: Operating System :: OS Independent
Classifier: Programming Language :: Python :: 3
Classifier: Programming Language :: Python :: 3.10
Classifier: Programming Language :: Python :: 3.11
Classifier: Programming Language :: Python :: 3.12
Classifier: Programming Language :: Python :: 3.13
Classifier: Programming Language :: Python :: 3.14
Classifier: Topic :: Internet :: WWW/HTTP
Classifier: Topic :: Software Development :: Libraries :: Python Modules
Classifier: Typing :: Typed
Requires-Dist: curl-cffi>=0.14.0
Requires-Dist: orjson>=3.11.5
Requires-Dist: pydantic>=2.12.5
Requires-Dist: fastmcp>=2.14.2 ; extra == 'mcp'
Requires-Python: >=3.10, <3.15
Project-URL: Changelog, https://github.com/henrique-coder/package-query/releases
Project-URL: Documentation, https://github.com/henrique-coder/package-query#readme
Project-URL: Homepage, https://github.com/henrique-coder/package-query
Project-URL: Issues, https://github.com/henrique-coder/package-query/issues
Project-URL: Repository, https://github.com/henrique-coder/package-query.git
Provides-Extra: mcp
